{"name":"ST11HivesDie","contentType":"TRIGGER","description":"","isEnabled":true,"initiallyOff":true,"runOnMapInit":true,"events":[{"name":"TriggerRegisterUnitEvent","type":"EVENT","isEnabled":true,"parameters":[{"type":"VARIABLE","value":"gg_unit_h04X_0173"},{"type":"PRESET","value":"UnitEventDeath"}]},{"name":"TriggerRegisterUnitEvent","type":"EVENT","isEnabled":true,"parameters":[{"type":"VARIABLE","value":"gg_unit_h04X_0148"},{"type":"PRESET","value":"UnitEventDeath"}]},{"name":"TriggerRegisterUnitEvent","type":"EVENT","isEnabled":true,"parameters":[{"type":"VARIABLE","value":"gg_unit_h04X_0172"},{"type":"PRESET","value":"UnitEventDeath"}]}],"conditions":[],"actions":[{"name":"IfThenElseMultiple","type":"ACTION","isEnabled":true,"parameters":[],"statements":[[{"name":"AndMultiple","type":"CONDITION","isEnabled":true,"parameters":[],"statements":[[{"name":"OperatorCompareBoolean","type":"CONDITION","isEnabled":true,"parameters":[{"type":"FUNCTION","value":"IsUnitAliveBJ","statement":{"type":"CALL","isEnabled":true,"name":"IsUnitAliveBJ","parameters":[{"type":"VARIABLE","value":"gg_unit_h04X_0172"}]}},{"type":"PRESET","value":"OperatorEqualENE"},{"type":"VALUE","value":"false"}]},{"name":"OperatorCompareBoolean","type":"CONDITION","isEnabled":true,"parameters":[{"type":"FUNCTION","value":"IsUnitAliveBJ","statement":{"type":"CALL","isEnabled":true,"name":"IsUnitAliveBJ","parameters":[{"type":"VARIABLE","value":"gg_unit_h04X_0148"}]}},{"type":"PRESET","value":"OperatorEqualENE"},{"type":"VALUE","value":"false"}]},{"name":"OperatorCompareBoolean","type":"CONDITION","isEnabled":true,"parameters":[{"type":"FUNCTION","value":"IsUnitAliveBJ","statement":{"type":"CALL","isEnabled":true,"name":"IsUnitAliveBJ","parameters":[{"type":"VARIABLE","value":"gg_unit_h04X_0173"}]}},{"type":"PRESET","value":"OperatorEqualENE"},{"type":"VALUE","value":"false"}]},{"name":"OperatorCompareBoolean","type":"CONDITION","isEnabled":true,"parameters":[{"type":"FUNCTION","value":"IsUnitAliveBJ","statement":{"type":"CALL","isEnabled":true,"name":"IsUnitAliveBJ","parameters":[{"type":"VARIABLE","value":"Playerhero","arrayIndex":{"type":"FUNCTION","value":"GetConvertedPlayerId","statement":{"type":"CALL","isEnabled":true,"name":"GetConvertedPlayerId","parameters":[{"type":"VARIABLE","value":"Mutant"}]}}}]}},{"type":"PRESET","value":"OperatorEqualENE"},{"type":"VALUE","value":"true"}]}]]}],[{"name":"CustomScriptCode","type":"ACTION","isEnabled":true,"parameters":[{"type":"VALUE","value":"call DestroyTrigger(GetTriggeringTrigger())"}]},{"name":"SetUnitOwner","type":"ACTION","isEnabled":true,"parameters":[{"type":"VARIABLE","value":"Playerhero","arrayIndex":{"type":"FUNCTION","value":"GetConvertedPlayerId","statement":{"type":"CALL","isEnabled":true,"name":"GetConvertedPlayerId","parameters":[{"type":"VARIABLE","value":"Mutant"}]}}},{"type":"PRESET","value":"PlayerNP"},{"type":"PRESET","value":"ChangeColorFalse"}]},{"name":"ForForceMultiple","type":"ACTION","isEnabled":true,"parameters":[{"type":"FUNCTION","value":"GetPlayersAll","statement":{"type":"CALL","isEnabled":true,"name":"GetPlayersAll","parameters":[]}}],"statements":[[{"name":"CustomScriptCode","type":"ACTION","isEnabled":true,"parameters":[{"type":"VALUE","value":"call DisplayTextToPlayer(GetEnumPlayer(), 0, 0, \"The Overlord has been slain! Flee his body or BE DOOMED TO A HORRIBLE DEATH.\")"}]}]]},{"name":"CustomScriptCode","type":"ACTION","isEnabled":true,"parameters":[{"type":"VALUE","value":"call DisplayTextToForce(GetForceOfPlayer(udg_Mutant), \"\\nDONT Panic.\\nYou have 35 seconds to kill every invader and win the game!\")"}]},{"name":"StartTimerBJ","type":"ACTION","isEnabled":true,"parameters":[{"type":"VARIABLE","value":"OverlordDeath_DestructionTimer"},{"type":"PRESET","value":"PeriodicOptionOneTime"},{"type":"VALUE","value":"35.00"}]},{"name":"CreateTimerDialogBJ","type":"ACTION","isEnabled":true,"parameters":[{"type":"FUNCTION","value":"GetLastCreatedTimerBJ","statement":{"type":"CALL","isEnabled":true,"name":"GetLastCreatedTimerBJ","parameters":[]}},{"type":"VALUE","value":"TRIGSTR_4087"}]},{"name":"SetVariable","type":"ACTION","isEnabled":true,"parameters":[{"type":"VARIABLE","value":"OverlordDeath_TimerWindow"},{"type":"FUNCTION","value":"GetLastCreatedTimerDialogBJ","statement":{"type":"CALL","isEnabled":true,"name":"GetLastCreatedTimerDialogBJ","parameters":[]}}]}]]}]}