{"name":"ST11BloodEffect","contentType":"TRIGGER","description":"","isEnabled":true,"initiallyOff":true,"runOnMapInit":true,"events":[{"name":"TriggerRegisterTimerEventPeriodic","type":"EVENT","isEnabled":true,"parameters":[{"type":"VALUE","value":"0.20"}]}],"conditions":[],"actions":[{"name":"SetVariable","type":"ACTION","isEnabled":true,"parameters":[{"type":"VARIABLE","value":"TempPoint"},{"type":"FUNCTION","value":"GetRandomLocInRect","statement":{"type":"CALL","isEnabled":true,"name":"GetRandomLocInRect","parameters":[{"type":"VARIABLE","value":"gg_rct_OverlordRect"}]}}]},{"name":"AddSpecialEffectLocBJ","type":"ACTION","isEnabled":true,"parameters":[{"type":"VARIABLE","value":"TempPoint"},{"type":"VALUE","value":"Objects\\Spawnmodels\\Human\\HumanLargeDeathExplode\\HumanLargeDeathExplode.mdl"}]},{"name":"CustomScriptCode","type":"ACTION","isEnabled":true,"parameters":[{"type":"VALUE","value":"call RemoveLocation(udg_TempPoint)"}]},{"name":"CustomScriptCode","type":"ACTION","isEnabled":true,"parameters":[{"type":"VALUE","value":"call SFXThreadClean()"}]}]}