{"name":"GITAddTestsToMedshops","contentType":"TRIGGER","description":"In this way, it is added via trigger (since the medshop now has the \"Sell Items\" ability for this to work), so as these items can be removed via trigger later ;)","isEnabled":true,"initiallyOff":false,"runOnMapInit":false,"events":[{"name":"MapInitializationEvent","type":"EVENT","isEnabled":true,"parameters":[]}],"conditions":[],"actions":[{"name":"SetVariable","type":"ACTION","isEnabled":true,"parameters":[{"type":"VARIABLE","value":"TempUnitGroup"},{"type":"FUNCTION","value":"GetUnitsOfTypeIdAll","statement":{"type":"CALL","isEnabled":true,"name":"GetUnitsOfTypeIdAll","parameters":[{"type":"VALUE","value":"h00G"}]}}]},{"name":"ForGroupMultiple","type":"ACTION","isEnabled":true,"parameters":[{"type":"VARIABLE","value":"TempUnitGroup"}],"statements":[[{"name":"AddItemToStockBJ","type":"ACTION","isEnabled":true,"parameters":[{"type":"VALUE","value":"I00M"},{"type":"FUNCTION","value":"GetEnumUnit","statement":{"type":"CALL","isEnabled":true,"name":"GetEnumUnit","parameters":[]}},{"type":"VALUE","value":"0"},{"type":"VALUE","value":"1"}]}]]},{"name":"AddItemToStockBJ","type":"ACTION","isEnabled":true,"parameters":[{"type":"VALUE","value":"I00M"},{"type":"VARIABLE","value":"gg_unit_h011_0100"},{"type":"VALUE","value":"0"},{"type":"VALUE","value":"99"}]},{"name":"CustomScriptCode","type":"ACTION","isEnabled":true,"parameters":[{"type":"VALUE","value":"call DestroyGroup(udg_TempUnitGroup)"}]}]}